README.rst
setup.py
smoke_zephyr/__init__.py
smoke_zephyr/argparse_types.py
smoke_zephyr/configuration.py
smoke_zephyr/job.py
smoke_zephyr/requirements.py
smoke_zephyr/utilities.py
smoke_zephyr.egg-info/PKG-INFO
smoke_zephyr.egg-info/SOURCES.txt
smoke_zephyr.egg-info/dependency_links.txt
smoke_zephyr.egg-info/top_level.txt