Metadata-Version: 1.2
Name: smoke-zephyr
Version: 1.4.1
Summary: This project provides a collection of miscellaneous Python utilities.
Home-page: https://github.com/zeroSteiner/smoke-zephyr
Author: Spencer McIntyre
Author-email: zeroSteiner@gmail.com
Maintainer: Spencer McIntyre
Maintainer-email: zeroSteiner@gmail.com
License: BSD
Platform: UNKNOWN
Classifier: Development Status :: 5 - Production/Stable
Classifier: Intended Audience :: Developers
Classifier: License :: OSI Approved :: BSD License
Classifier: Operating System :: POSIX
Classifier: Programming Language :: Python
Classifier: Programming Language :: Python :: 2.7
Classifier: Programming Language :: Python :: 3.3
Classifier: Programming Language :: Python :: 3.4
Classifier: Programming Language :: Python :: 3.5
Classifier: Programming Language :: Python :: 3.6
Classifier: Programming Language :: Python :: 3.7
